astdys/__init__.py
astdys/astdys.py
astdys/catalog.py
astdys/util.py
astdys-1.0.0.dist-info/LICENSE
astdys-1.0.0.dist-info/METADATA
astdys-1.0.0.dist-info/WHEEL
astdys-1.0.0.dist-info/RECORD
